pfpmodel/__init__.py
pfpmodel/pfpgraph.py
pfpmodel-1.1.4.dev1.dist-info/DESCRIPTION.rst
pfpmodel-1.1.4.dev1.dist-info/METADATA
pfpmodel-1.1.4.dev1.dist-info/RECORD
pfpmodel-1.1.4.dev1.dist-info/WHEEL
pfpmodel-1.1.4.dev1.dist-info/metadata.json
pfpmodel-1.1.4.dev1.dist-info/top_level.txt
